{
  "1995": {
    "idps": 0,
    "poc": 0,
    "refugees": 343
  },
  "1996": {
    "idps": 0,
    "poc": 0,
    "refugees": 397
  },
  "1997": {
    "idps": 0,
    "poc": 0,
    "refugees": 473
  },
  "1998": {
    "idps": 0,
    "poc": 0,
    "refugees": 420
  },
  "1999": {
    "idps": 0,
    "poc": 0,
    "refugees": 429
  },
  "2000": {
    "idps": 0,
    "poc": 0,
    "refugees": 509
  },
  "2001": {
    "idps": 0,
    "poc": 0,
    "refugees": 529
  },
  "2002": {
    "idps": 0,
    "poc": 0,
    "refugees": 552
  },
  "2003": {
    "idps": 0,
    "poc": 0,
    "refugees": 591
  },
  "2004": {
    "idps": 0,
    "poc": 0,
    "refugees": 546
  },
  "2005": {
    "idps": 0,
    "poc": 0,
    "refugees": 477
  },
  "2006": {
    "idps": 0,
    "poc": 0,
    "refugees": 461
  },
  "2007": {
    "idps": 0,
    "poc": 0,
    "refugees": 407
  },
  "2008": {
    "idps": 0,
    "poc": 0,
    "refugees": 384
  },
  "2009": {
    "idps": 0,
    "poc": 0,
    "refugees": 344
  },
  "2010": {
    "idps": 0,
    "poc": 0,
    "refugees": 305
  },
  "2011": {
    "idps": 0,
    "poc": 0,
    "refugees": 258
  },
  "2012": {
    "idps": 0,
    "poc": 0,
    "refugees": 228
  },
  "2013": {
    "idps": 0,
    "poc": 0,
    "refugees": 200
  },
  "2014": {
    "idps": 0,
    "poc": 0,
    "refugees": 163
  }
}