{
  "1995": {
    "idps": 0,
    "poc": 0,
    "refugees": 1939
  },
  "1996": {
    "idps": 0,
    "poc": 0,
    "refugees": 4754
  },
  "1997": {
    "idps": 0,
    "poc": 0,
    "refugees": 3059
  },
  "1998": {
    "idps": 0,
    "poc": 1,
    "refugees": 3999
  },
  "1999": {
    "idps": 0,
    "poc": 0,
    "refugees": 4441
  },
  "2000": {
    "idps": 0,
    "poc": 0,
    "refugees": 5742
  },
  "2001": {
    "idps": 0,
    "poc": 0,
    "refugees": 6084
  },
  "2002": {
    "idps": 0,
    "poc": 0,
    "refugees": 24572
  },
  "2003": {
    "idps": 0,
    "poc": 0,
    "refugees": 24428
  },
  "2004": {
    "idps": 0,
    "poc": 0,
    "refugees": 23890
  },
  "2005": {
    "idps": 0,
    "poc": 0,
    "refugees": 22128
  },
  "2006": {
    "idps": 0,
    "poc": 0,
    "refugees": 13253
  },
  "2007": {
    "idps": 0,
    "poc": 0,
    "refugees": 13904
  },
  "2008": {
    "idps": 0,
    "poc": 0,
    "refugees": 14169
  },
  "2009": {
    "idps": 0,
    "poc": 0,
    "refugees": 15609
  },
  "2010": {
    "idps": 0,
    "poc": 0,
    "refugees": 15642
  },
  "2011": {
    "idps": 0,
    "poc": 0,
    "refugees": 17141
  },
  "2012": {
    "idps": 0,
    "poc": 0,
    "refugees": 18021
  },
  "2013": {
    "idps": 0,
    "poc": 0,
    "refugees": 31176
  },
  "2014": {
    "idps": 1188018,
    "poc": 70008,
    "refugees": 90865
  }
}